[{"s": "garik-v-kartridzhe-chto-delat", "t": "Гарик в картридже: причины, как устранить и что делать дальше", "i": "🛒", "c": "avtozapchasti-i-raskhodniki"}, {"s": "garik-v-vejpe-eto", "t": "Гарик в вейпе: что это, причины и способы убрать", "i": "📁", "c": "drugoe"}, {"s": "garik-na-novom-isparitele", "t": "Гарик после замены испарителя: как правильно подготовить койл", "i": "📁", "c": "drugoe"}, {"s": "garantiya-na-radiator-okhlazhdeniya-avtomobilya", "t": "Гарантия на радиатор охлаждения: сроки, условия и возврат", "i": "🚗", "c": "sistema-okhlazhdeniya-avto"}]